{"cameraMode":{"drawMode":0,"name":"Shaded","section":"Shading Mode"},"sceneLighting":true,"audioPlay":false,"sceneViewState":{"m_AlwaysRefresh":false,"showFog":true,"showSkybox":true,"showFlares":true,"showImageEffects":true,"showParticleSystems":true,"showVisualEffectGraphs":true,"m_FxEnabled":true},"in2DMode":false,"pivot":{"x":7.19441032409668,"y":12.818435668945313,"z":-18.30266571044922},"rotation":{"x":0.4827157258987427,"y":0.02626587636768818,"z":-0.014485822059214116,"w":0.8752655982971191},"size":37.60670471191406,"orthographic":false}