{"cameraMode":{"drawMode":0,"name":"Shaded","section":"Shading Mode"},"sceneLighting":false,"audioPlay":false,"sceneViewState":{"m_AlwaysRefresh":false,"showFog":true,"showSkybox":false,"showFlares":true,"showImageEffects":true,"showParticleSystems":true,"showVisualEffectGraphs":true,"m_FxEnabled":true},"in2DMode":false,"pivot":{"x":1.5518834590911866,"y":0.9633125066757202,"z":-0.14702913165092469},"rotation":{"x":0.006257631350308657,"y":-0.9935675859451294,"z":0.0695641040802002,"w":0.0893709734082222},"size":10.0,"orthographic":true}